README.md
setup.py
llama/__init__.py
llama/actions.py
llama/actions_test.py
llama/mqtt.py
llama/mqtt_test.py
llama_mqtt.egg-info/PKG-INFO
llama_mqtt.egg-info/SOURCES.txt
llama_mqtt.egg-info/dependency_links.txt
llama_mqtt.egg-info/requires.txt
llama_mqtt.egg-info/top_level.txt