Metadata-Version: 1.2
Name: llama-mqtt
Version: 0.4.1
Summary: An opinionated library for writing MQTT services
Home-page: https://github.com/cameliot/llama
Author: Matthias Hannig
Author-email: matthias@hannig.cc
License: BSD
Keywords: mqtt,actor,react,service
Platform: UNKNOWN
Classifier: Development Status :: 4 - Beta
Classifier: Intended Audience :: Developers
Classifier: License :: OSI Approved :: BSD License
Classifier: Programming Language :: Python :: 3
Classifier: Topic :: Software Development :: Libraries
Classifier: Topic :: Software Development :: Libraries :: Python Modules
Requires-Python: >=3
